Metadata-Version: 2.1
Name: solo-sc
Version: 1.3
Summary: Neural network classifiers for doublets
Home-page: http://github.com/calico/solo
Author: David Kelley, Nick Bernstein
Author-email: nicholas@calicolabs.com
License: Apache
Download-URL: https://github.com/calico/solo/archive/1.2.tar.gz
Platform: UNKNOWN
Classifier: Environment :: Console
Classifier: Intended Audience :: Science/Research
Classifier: Topic :: Scientific/Engineering :: Bio-Informatics
Requires-Python: >=3.7
